{
  "data": {
    "Default_": [
      0,
      0,
      0
    ],
    "MasterFile": "Metadata/Terrain/Gallows/Act4_Interlude/Part3/P3_7/master.tsi"
  },
  "edge_count": 49,
  "edge_types": {
    "Metadata/Terrain/Gallows/Act3/3_15/Graphs/corridor_rooms.et": {
      "id": "LibraryCorridorRooms",
      "color": null
    },
    "Metadata/Terrain/Tools/void.et": {
      "id": "void",
      "color": "#FF141414"
    }
  },
  "edges": [
    {
      "from_": 2,
      "to": 1,
      "path": [],
      "unknown": [
        100,
        0,
        0,
        "Metadata/Terrain/Gallows/Act3/3_15/Graphs/corridor_rooms.et",
        0,
        60,
        1,
        "",
        0,
        "",
        0,
        0,
        "P",
        "N",
        1
      ],
      "edge_type": "Metadata/Terrain/Gallows/Act3/3_15/Graphs/corridor_rooms.et",
      "color": null
    },
    {
      "from_": 6,
      "to": 3,
      "path": [],
      "unknown": [
        100,
        0,
        0,
        "Metadata/Terrain/Gallows/Act3/3_15/Graphs/corridor_rooms.et",
        0,
        60,
        1,
        "Metadata/Terrain/Dungeon/rooms.et",
        0,
        "",
        0,
        0,
        "P",
        "N",
        1
      ],
      "edge_type": "Metadata/Terrain/Gallows/Act3/3_15/Graphs/corridor_rooms.et",
      "color": null
    },
    {
      "from_": 7,
      "to": 5,
      "path": [],
      "unknown": [
        100,
        0,
        0,
        "Metadata/Terrain/Gallows/Act3/3_15/Graphs/corridor_rooms.et",
        0,
        60,
        1,
        "Metadata/Terrain/Dungeon/rooms.et",
        0,
        "",
        0,
        0,
        "P",
        "N",
        1
      ],
      "edge_type": "Metadata/Terrain/Gallows/Act3/3_15/Graphs/corridor_rooms.et",
      "color": null
    },
    {
      "from_": 5,
      "to": 4,
      "path": [],
      "unknown": [
        100,
        0,
        0,
        "Metadata/Terrain/Gallows/Act3/3_15/Graphs/corridor_rooms.et",
        0,
        60,
        1,
        "",
        0,
        "",
        0,
        0,
        "P",
        "N",
        1
      ],
      "edge_type": "Metadata/Terrain/Gallows/Act3/3_15/Graphs/corridor_rooms.et",
      "color": null
    },
    {
      "from_": 4,
      "to": 6,
      "path": [],
      "unknown": [
        100,
        0,
        0,
        "Metadata/Terrain/Gallows/Act3/3_15/Graphs/corridor_rooms.et",
        0,
        60,
        1,
        "",
        0,
        "",
        0,
        0,
        "P",
        "N",
        1
      ],
      "edge_type": "Metadata/Terrain/Gallows/Act3/3_15/Graphs/corridor_rooms.et",
      "color": null
    },
    {
      "from_": 0,
      "to": 3,
      "path": [],
      "unknown": [
        100,
        0,
        0,
        "Metadata/Terrain/Gallows/Act3/3_15/Graphs/corridor_rooms.et",
        0,
        60,
        1,
        "",
        0,
        "",
        0,
        0,
        "P",
        "N",
        1
      ],
      "edge_type": "Metadata/Terrain/Gallows/Act3/3_15/Graphs/corridor_rooms.et",
      "color": null
    },
    {
      "from_": 2,
      "to": 8,
      "path": [],
      "unknown": [
        100,
        0,
        0,
        "Metadata/Terrain/Gallows/Act3/3_15/Graphs/corridor_rooms.et",
        0,
        60,
        1,
        "",
        0,
        "",
        0,
        0,
        "P",
        "N",
        1
      ],
      "edge_type": "Metadata/Terrain/Gallows/Act3/3_15/Graphs/corridor_rooms.et",
      "color": null
    },
    {
      "from_": 5,
      "to": 9,
      "path": [],
      "unknown": [
        100,
        0,
        0,
        "Metadata/Terrain/Gallows/Act3/3_15/Graphs/corridor_rooms.et",
        0,
        60,
        1,
        "",
        0,
        "",
        0,
        0,
        "P",
        "N",
        1
      ],
      "edge_type": "Metadata/Terrain/Gallows/Act3/3_15/Graphs/corridor_rooms.et",
      "color": null
    },
    {
      "from_": 9,
      "to": 1,
      "path": [],
      "unknown": [
        100,
        0,
        0,
        "Metadata/Terrain/Gallows/Act3/3_15/Graphs/corridor_rooms.et",
        0,
        60,
        1,
        "",
        0,
        "",
        0,
        0,
        "P",
        "N",
        1
      ],
      "edge_type": "Metadata/Terrain/Gallows/Act3/3_15/Graphs/corridor_rooms.et",
      "color": null
    },
    {
      "from_": 13,
      "to": 11,
      "path": [],
      "unknown": [
        100,
        0,
        0,
        "Metadata/Terrain/Gallows/Act3/3_15/Graphs/corridor_rooms.et",
        0,
        60,
        1,
        "",
        0,
        "",
        0,
        0,
        "P",
        "N",
        1
      ],
      "edge_type": "Metadata/Terrain/Gallows/Act3/3_15/Graphs/corridor_rooms.et",
      "color": null
    },
    {
      "from_": 12,
      "to": 10,
      "path": [],
      "unknown": [
        100,
        0,
        0,
        "Metadata/Terrain/Gallows/Act3/3_15/Graphs/corridor_rooms.et",
        0,
        60,
        1,
        "",
        0,
        "",
        0,
        0,
        "P",
        "N",
        1
      ],
      "edge_type": "Metadata/Terrain/Gallows/Act3/3_15/Graphs/corridor_rooms.et",
      "color": null
    },
    {
      "from_": 3,
      "to": 7,
      "path": [],
      "unknown": [
        100,
        0,
        0,
        "Metadata/Terrain/Gallows/Act3/3_15/Graphs/corridor_rooms.et",
        0,
        60,
        1,
        "",
        0,
        "",
        0,
        0,
        "P",
        "N",
        1
      ],
      "edge_type": "Metadata/Terrain/Gallows/Act3/3_15/Graphs/corridor_rooms.et",
      "color": null
    },
    {
      "from_": 2,
      "to": 4,
      "path": [],
      "unknown": [
        100,
        0,
        0,
        "Metadata/Terrain/Gallows/Act3/3_15/Graphs/corridor_rooms.et",
        0,
        60,
        1,
        "",
        0,
        "",
        0,
        0,
        "P",
        "N",
        1
      ],
      "edge_type": "Metadata/Terrain/Gallows/Act3/3_15/Graphs/corridor_rooms.et",
      "color": null
    },
    {
      "from_": 12,
      "to": 14,
      "path": [],
      "unknown": [
        100,
        0,
        0,
        "Metadata/Terrain/Gallows/Act3/3_15/Graphs/corridor_rooms.et",
        0,
        60,
        1,
        "",
        0,
        "",
        0,
        0,
        "I",
        "N",
        1
      ],
      "edge_type": "Metadata/Terrain/Gallows/Act3/3_15/Graphs/corridor_rooms.et",
      "color": null
    },
    {
      "from_": 15,
      "to": 10,
      "path": [],
      "unknown": [
        100,
        0,
        0,
        "Metadata/Terrain/Gallows/Act3/3_15/Graphs/corridor_rooms.et",
        0,
        60,
        1,
        "",
        0,
        "",
        0,
        0,
        "P",
        "N",
        1
      ],
      "edge_type": "Metadata/Terrain/Gallows/Act3/3_15/Graphs/corridor_rooms.et",
      "color": null
    },
    {
      "from_": 13,
      "to": 16,
      "path": [],
      "unknown": [
        100,
        0,
        0,
        "Metadata/Terrain/Gallows/Act3/3_15/Graphs/corridor_rooms.et",
        0,
        60,
        1,
        "",
        0,
        "",
        0,
        0,
        "P",
        "N",
        1
      ],
      "edge_type": "Metadata/Terrain/Gallows/Act3/3_15/Graphs/corridor_rooms.et",
      "color": null
    },
    {
      "from_": 16,
      "to": 10,
      "path": [],
      "unknown": [
        100,
        0,
        0,
        "Metadata/Terrain/Gallows/Act3/3_15/Graphs/corridor_rooms.et",
        0,
        60,
        1,
        "",
        0,
        "",
        0,
        0,
        "P",
        "N",
        1
      ],
      "edge_type": "Metadata/Terrain/Gallows/Act3/3_15/Graphs/corridor_rooms.et",
      "color": null
    },
    {
      "from_": 18,
      "to": 15,
      "path": [],
      "unknown": [
        100,
        0,
        0,
        "Metadata/Terrain/Gallows/Act3/3_15/Graphs/corridor_rooms.et",
        0,
        60,
        1,
        "",
        0,
        "",
        0,
        0,
        "P",
        "N",
        1
      ],
      "edge_type": "Metadata/Terrain/Gallows/Act3/3_15/Graphs/corridor_rooms.et",
      "color": null
    },
    {
      "from_": 1,
      "to": 12,
      "path": [],
      "unknown": [
        100,
        0,
        0,
        "Metadata/Terrain/Gallows/Act3/3_15/Graphs/corridor_rooms.et",
        0,
        60,
        1,
        "",
        0,
        "",
        0,
        0,
        "P",
        "N",
        1
      ],
      "edge_type": "Metadata/Terrain/Gallows/Act3/3_15/Graphs/corridor_rooms.et",
      "color": null
    },
    {
      "from_": 17,
      "to": 19,
      "path": [],
      "unknown": [
        100,
        0,
        0,
        "Metadata/Terrain/Gallows/Act3/3_15/Graphs/corridor_rooms.et",
        0,
        60,
        1,
        "",
        0,
        "",
        0,
        0,
        "P",
        "N",
        1
      ],
      "edge_type": "Metadata/Terrain/Gallows/Act3/3_15/Graphs/corridor_rooms.et",
      "color": null
    },
    {
      "from_": 19,
      "to": 15,
      "path": [],
      "unknown": [
        100,
        0,
        0,
        "Metadata/Terrain/Gallows/Act3/3_15/Graphs/corridor_rooms.et",
        0,
        60,
        1,
        "",
        0,
        "",
        0,
        0,
        "P",
        "N",
        1
      ],
      "edge_type": "Metadata/Terrain/Gallows/Act3/3_15/Graphs/corridor_rooms.et",
      "color": null
    },
    {
      "from_": 14,
      "to": 17,
      "path": [],
      "unknown": [
        100,
        0,
        0,
        "Metadata/Terrain/Gallows/Act3/3_15/Graphs/corridor_rooms.et",
        0,
        60,
        1,
        "",
        0,
        "",
        0,
        0,
        "P",
        "N",
        1
      ],
      "edge_type": "Metadata/Terrain/Gallows/Act3/3_15/Graphs/corridor_rooms.et",
      "color": null
    },
    {
      "from_": 9,
      "to": 20,
      "path": [],
      "unknown": [
        100,
        0,
        0,
        "Metadata/Terrain/Gallows/Act3/3_15/Graphs/corridor_rooms.et",
        0,
        60,
        1,
        "",
        0,
        "",
        0,
        0,
        "P",
        "N",
        1
      ],
      "edge_type": "Metadata/Terrain/Gallows/Act3/3_15/Graphs/corridor_rooms.et",
      "color": null
    },
    {
      "from_": 21,
      "to": 19,
      "path": [],
      "unknown": [
        100,
        0,
        0,
        "Metadata/Terrain/Gallows/Act3/3_15/Graphs/corridor_rooms.et",
        0,
        60,
        1,
        "",
        0,
        "",
        0,
        0,
        "P",
        "N",
        1
      ],
      "edge_type": "Metadata/Terrain/Gallows/Act3/3_15/Graphs/corridor_rooms.et",
      "color": null
    },
    {
      "from_": 22,
      "to": 23,
      "path": [],
      "unknown": [
        100,
        0,
        0,
        "Metadata/Terrain/Tools/void.et",
        0,
        0,
        0,
        "",
        0,
        "",
        0,
        0,
        "P",
        "V",
        1
      ],
      "edge_type": "Metadata/Terrain/Tools/void.et",
      "color": "#FF141414"
    },
    {
      "from_": 23,
      "to": 24,
      "path": [],
      "unknown": [
        100,
        0,
        0,
        "Metadata/Terrain/Tools/void.et",
        0,
        0,
        0,
        "",
        0,
        "",
        0,
        0,
        "P",
        "V",
        1
      ],
      "edge_type": "Metadata/Terrain/Tools/void.et",
      "color": "#FF141414"
    },
    {
      "from_": 24,
      "to": 25,
      "path": [],
      "unknown": [
        100,
        0,
        0,
        "Metadata/Terrain/Tools/void.et",
        0,
        0,
        0,
        "",
        0,
        "",
        0,
        0,
        "P",
        "V",
        1
      ],
      "edge_type": "Metadata/Terrain/Tools/void.et",
      "color": "#FF141414"
    },
    {
      "from_": 44,
      "to": 26,
      "path": [],
      "unknown": [
        100,
        0,
        0,
        "Metadata/Terrain/Tools/void.et",
        0,
        0,
        0,
        "",
        0,
        "",
        0,
        0,
        "P",
        "V",
        1
      ],
      "edge_type": "Metadata/Terrain/Tools/void.et",
      "color": "#FF141414"
    },
    {
      "from_": 45,
      "to": 27,
      "path": [],
      "unknown": [
        100,
        0,
        0,
        "Metadata/Terrain/Tools/void.et",
        0,
        0,
        0,
        "",
        0,
        "",
        0,
        0,
        "P",
        "V",
        1
      ],
      "edge_type": "Metadata/Terrain/Tools/void.et",
      "color": "#FF141414"
    },
    {
      "from_": 27,
      "to": 28,
      "path": [],
      "unknown": [
        100,
        0,
        0,
        "Metadata/Terrain/Tools/void.et",
        0,
        0,
        0,
        "",
        0,
        "",
        0,
        0,
        "P",
        "V",
        1
      ],
      "edge_type": "Metadata/Terrain/Tools/void.et",
      "color": "#FF141414"
    },
    {
      "from_": 29,
      "to": 30,
      "path": [],
      "unknown": [
        100,
        0,
        0,
        "Metadata/Terrain/Tools/void.et",
        0,
        0,
        0,
        "",
        0,
        "",
        0,
        0,
        "P",
        "V",
        1
      ],
      "edge_type": "Metadata/Terrain/Tools/void.et",
      "color": "#FF141414"
    },
    {
      "from_": 30,
      "to": 31,
      "path": [],
      "unknown": [
        100,
        0,
        0,
        "Metadata/Terrain/Tools/void.et",
        0,
        0,
        0,
        "",
        0,
        "",
        0,
        0,
        "P",
        "V",
        1
      ],
      "edge_type": "Metadata/Terrain/Tools/void.et",
      "color": "#FF141414"
    },
    {
      "from_": 31,
      "to": 32,
      "path": [],
      "unknown": [
        100,
        0,
        0,
        "Metadata/Terrain/Tools/void.et",
        0,
        0,
        0,
        "",
        0,
        "",
        0,
        0,
        "P",
        "V",
        1
      ],
      "edge_type": "Metadata/Terrain/Tools/void.et",
      "color": "#FF141414"
    },
    {
      "from_": 32,
      "to": 33,
      "path": [],
      "unknown": [
        100,
        0,
        0,
        "Metadata/Terrain/Tools/void.et",
        0,
        0,
        0,
        "",
        0,
        "",
        0,
        0,
        "P",
        "V",
        1
      ],
      "edge_type": "Metadata/Terrain/Tools/void.et",
      "color": "#FF141414"
    },
    {
      "from_": 33,
      "to": 34,
      "path": [],
      "unknown": [
        100,
        0,
        0,
        "Metadata/Terrain/Tools/void.et",
        0,
        0,
        0,
        "",
        0,
        "",
        0,
        0,
        "P",
        "V",
        1
      ],
      "edge_type": "Metadata/Terrain/Tools/void.et",
      "color": "#FF141414"
    },
    {
      "from_": 34,
      "to": 35,
      "path": [],
      "unknown": [
        100,
        0,
        0,
        "Metadata/Terrain/Tools/void.et",
        0,
        0,
        0,
        "",
        0,
        "",
        0,
        0,
        "P",
        "V",
        1
      ],
      "edge_type": "Metadata/Terrain/Tools/void.et",
      "color": "#FF141414"
    },
    {
      "from_": 48,
      "to": 37,
      "path": [],
      "unknown": [
        100,
        0,
        0,
        "Metadata/Terrain/Tools/void.et",
        0,
        0,
        0,
        "",
        0,
        "",
        0,
        0,
        "P",
        "V",
        1
      ],
      "edge_type": "Metadata/Terrain/Tools/void.et",
      "color": "#FF141414"
    },
    {
      "from_": 49,
      "to": 38,
      "path": [],
      "unknown": [
        100,
        0,
        0,
        "Metadata/Terrain/Tools/void.et",
        0,
        0,
        0,
        "",
        0,
        "",
        0,
        0,
        "P",
        "V",
        1
      ],
      "edge_type": "Metadata/Terrain/Tools/void.et",
      "color": "#FF141414"
    },
    {
      "from_": 38,
      "to": 39,
      "path": [],
      "unknown": [
        100,
        0,
        0,
        "Metadata/Terrain/Tools/void.et",
        0,
        0,
        0,
        "",
        0,
        "",
        0,
        0,
        "P",
        "V",
        1
      ],
      "edge_type": "Metadata/Terrain/Tools/void.et",
      "color": "#FF141414"
    },
    {
      "from_": 36,
      "to": 40,
      "path": [],
      "unknown": [
        100,
        0,
        0,
        "Metadata/Terrain/Tools/void.et",
        0,
        0,
        0,
        "",
        0,
        "",
        0,
        0,
        "P",
        "V",
        1
      ],
      "edge_type": "Metadata/Terrain/Tools/void.et",
      "color": "#FF141414"
    },
    {
      "from_": 36,
      "to": 41,
      "path": [],
      "unknown": [
        100,
        0,
        0,
        "Metadata/Terrain/Tools/void.et",
        0,
        0,
        0,
        "",
        0,
        "",
        0,
        0,
        "P",
        "V",
        1
      ],
      "edge_type": "Metadata/Terrain/Tools/void.et",
      "color": "#FF141414"
    },
    {
      "from_": 41,
      "to": 42,
      "path": [],
      "unknown": [
        100,
        0,
        0,
        "Metadata/Terrain/Tools/void.et",
        0,
        0,
        0,
        "",
        0,
        "",
        0,
        0,
        "P",
        "V",
        1
      ],
      "edge_type": "Metadata/Terrain/Tools/void.et",
      "color": "#FF141414"
    },
    {
      "from_": 35,
      "to": 43,
      "path": [],
      "unknown": [
        100,
        0,
        0,
        "Metadata/Terrain/Tools/void.et",
        0,
        0,
        0,
        "",
        0,
        "",
        0,
        0,
        "P",
        "V",
        1
      ],
      "edge_type": "Metadata/Terrain/Tools/void.et",
      "color": "#FF141414"
    },
    {
      "from_": 25,
      "to": 44,
      "path": [],
      "unknown": [
        100,
        0,
        0,
        "Metadata/Terrain/Tools/void.et",
        0,
        0,
        0,
        "",
        0,
        "",
        0,
        0,
        "P",
        "V",
        1
      ],
      "edge_type": "Metadata/Terrain/Tools/void.et",
      "color": "#FF141414"
    },
    {
      "from_": 26,
      "to": 45,
      "path": [],
      "unknown": [
        100,
        0,
        0,
        "Metadata/Terrain/Tools/void.et",
        0,
        0,
        0,
        "",
        0,
        "",
        0,
        0,
        "P",
        "V",
        1
      ],
      "edge_type": "Metadata/Terrain/Tools/void.et",
      "color": "#FF141414"
    },
    {
      "from_": 43,
      "to": 46,
      "path": [],
      "unknown": [
        100,
        0,
        0,
        "Metadata/Terrain/Tools/void.et",
        0,
        0,
        0,
        "",
        0,
        "",
        0,
        0,
        "P",
        "V",
        1
      ],
      "edge_type": "Metadata/Terrain/Tools/void.et",
      "color": "#FF141414"
    },
    {
      "from_": 39,
      "to": 47,
      "path": [],
      "unknown": [
        100,
        0,
        0,
        "Metadata/Terrain/Tools/void.et",
        0,
        0,
        0,
        "",
        0,
        "",
        0,
        0,
        "P",
        "V",
        1
      ],
      "edge_type": "Metadata/Terrain/Tools/void.et",
      "color": "#FF141414"
    },
    {
      "from_": 40,
      "to": 48,
      "path": [],
      "unknown": [
        100,
        0,
        0,
        "Metadata/Terrain/Tools/void.et",
        0,
        0,
        0,
        "",
        0,
        "",
        0,
        0,
        "P",
        "V",
        1
      ],
      "edge_type": "Metadata/Terrain/Tools/void.et",
      "color": "#FF141414"
    },
    {
      "from_": 37,
      "to": 49,
      "path": [],
      "unknown": [
        100,
        0,
        0,
        "Metadata/Terrain/Tools/void.et",
        0,
        0,
        0,
        "",
        0,
        "",
        0,
        0,
        "P",
        "V",
        1
      ],
      "edge_type": "Metadata/Terrain/Tools/void.et",
      "color": "#FF141414"
    }
  ],
  "fill_tiles": [
    {
      "file": "default",
      "prefix": null,
      "suffix": null,
      "tile_tag": null,
      "room_tag": null,
      "tile_tgt": null,
      "tile_parent": null
    },
    {
      "file": "Metadata/Terrain/Dungeon/NextFeatures/dungeon_blank_fill.tdt",
      "prefix": [
        "1"
      ],
      "suffix": null,
      "tile_tag": null,
      "room_tag": null,
      "tile_tgt": "Art/Models/Terrain/Jungle/Tiles/VaalInterior/dungeon_blank_fill.tgt",
      "tile_parent": null
    },
    {
      "file": "ArchivesHallGround",
      "prefix": null,
      "suffix": null,
      "tile_tag": null,
      "room_tag": null,
      "tile_tgt": null,
      "tile_parent": null
    },
    {
      "file": "Metadata/Terrain/Dungeon/NextFeatures/dungeon_blank_fill.tdt",
      "prefix": [
        "1"
      ],
      "suffix": null,
      "tile_tag": null,
      "room_tag": null,
      "tile_tgt": "Art/Models/Terrain/Jungle/Tiles/VaalInterior/dungeon_blank_fill.tgt",
      "tile_parent": null
    },
    {
      "file": "BlackInsideWall",
      "prefix": null,
      "suffix": null,
      "tile_tag": null,
      "room_tag": null,
      "tile_tgt": null,
      "tile_parent": null
    },
    {
      "file": "Metadata/Terrain/Dungeon/black.tdt",
      "prefix": [
        "1"
      ],
      "suffix": null,
      "tile_tag": null,
      "room_tag": null,
      "tile_tgt": "Art/Models/Terrain/IncaDungeon/dungeon_blackness_v01_01.tgt",
      "tile_parent": null
    }
  ],
  "master": {
    "ChestData": "chests.cht",
    "Doodads": "doodads.ddt",
    "EdgeCombination": "combination.ecf",
    "FillTiles": "random_fill_tiles.gft",
    "MaterialsList": "materials.mtd",
    "OuterGroundType": "Metadata/Terrain/black_inside_wall.gt",
    "Reskin": null,
    "RoomSet": "generate.rs",
    "TileSet": "tiles.tst",
    "version": null,
    "StoreyHeight": null,
    "RoomUnitSize": null,
    "RoomOverlap": null,
    "OuterBufferSize": null,
    "EdgePoints": null,
    "Decals": null,
    "Overlays": "overlays.toy",
    "RestrictedGTs": null,
    "EnvironmentPreload": null,
    "Critters": "critters.clt",
    "FileGroups": null
  },
  "node_count": 50,
  "numbers": [
    0
  ],
  "nodes": [
    {
      "numbers": [
        5
      ],
      "room": "entrance",
      "strings": [
        "default",
        "entrance1"
      ],
      "transform": "I",
      "unknown": [
        100,
        0,
        0,
        0,
        0,
        0,
        0,
        0,
        0,
        "N",
        1
      ],
      "x": 150,
      "y": 12
    },
    {
      "numbers": [
        8,
        18,
        0
      ],
      "room": "",
      "strings": [],
      "transform": "(any)",
      "unknown": [
        100,
        0,
        0,
        0,
        0,
        0,
        0,
        0,
        0,
        "N",
        1
      ],
      "x": 173,
      "y": 196
    },
    {
      "numbers": [
        12,
        0,
        6
      ],
      "room": "",
      "strings": [],
      "transform": "(any)",
      "unknown": [
        100,
        0,
        0,
        0,
        0,
        0,
        0,
        0,
        0,
        "N",
        1
      ],
      "x": 127,
      "y": 196
    },
    {
      "numbers": [
        5,
        11,
        1
      ],
      "room": "",
      "strings": [],
      "transform": "(any)",
      "unknown": [
        100,
        0,
        0,
        0,
        0,
        0,
        0,
        0,
        0,
        "N",
        1
      ],
      "x": 173,
      "y": 81
    },
    {
      "numbers": [
        4,
        3,
        12
      ],
      "room": "feature",
      "strings": [],
      "transform": "R90",
      "unknown": [
        100,
        0,
        0,
        0,
        0,
        0,
        0,
        0,
        0,
        "N",
        1
      ],
      "x": 104,
      "y": 104
    },
    {
      "numbers": [
        2,
        7,
        3
      ],
      "room": "feature",
      "strings": [],
      "transform": "R90",
      "unknown": [
        100,
        0,
        0,
        0,
        0,
        0,
        0,
        0,
        0,
        "N",
        1
      ],
      "x": 196,
      "y": 104
    },
    {
      "numbers": [
        1,
        4
      ],
      "room": "",
      "strings": [],
      "transform": "(any)",
      "unknown": [
        100,
        0,
        0,
        0,
        0,
        0,
        0,
        0,
        0,
        "N",
        1
      ],
      "x": 127,
      "y": 81
    },
    {
      "numbers": [
        2,
        11
      ],
      "room": "",
      "strings": [],
      "transform": "(any)",
      "unknown": [
        100,
        0,
        0,
        0,
        0,
        0,
        0,
        0,
        0,
        "N",
        1
      ],
      "x": 219,
      "y": 81
    },
    {
      "numbers": [
        6
      ],
      "room": "vault1",
      "strings": [
        "unique1"
      ],
      "transform": "(best)",
      "unknown": [
        100,
        0,
        0,
        0,
        0,
        0,
        0,
        0,
        0,
        "N",
        0
      ],
      "x": 58,
      "y": 196
    },
    {
      "numbers": [
        7,
        22,
        8
      ],
      "room": "",
      "strings": [],
      "transform": "(best)",
      "unknown": [
        100,
        0,
        0,
        0,
        0,
        0,
        0,
        0,
        0,
        "N",
        0
      ],
      "x": 219,
      "y": 196
    },
    {
      "numbers": [
        10,
        16,
        14
      ],
      "room": "feature",
      "strings": [],
      "transform": "I",
      "unknown": [
        100,
        0,
        0,
        0,
        0,
        0,
        0,
        0,
        0,
        "N",
        1
      ],
      "x": 127,
      "y": 311
    },
    {
      "numbers": [
        9
      ],
      "room": "boss",
      "strings": [
        "telepad1",
        "teleport1disabled-Arena"
      ],
      "transform": "R270",
      "unknown": [
        100,
        0,
        0,
        0,
        0,
        0,
        0,
        0,
        0,
        "N",
        0
      ],
      "x": 242,
      "y": 265
    },
    {
      "numbers": [
        18,
        10,
        13
      ],
      "room": "feature",
      "strings": [],
      "transform": "I",
      "unknown": [
        100,
        0,
        0,
        0,
        0,
        0,
        0,
        0,
        0,
        "N",
        1
      ],
      "x": 127,
      "y": 219
    },
    {
      "numbers": [
        9,
        15
      ],
      "room": "",
      "strings": [],
      "transform": "(best)",
      "unknown": [
        100,
        0,
        0,
        0,
        0,
        0,
        0,
        0,
        0,
        "N",
        0
      ],
      "x": 219,
      "y": 288
    },
    {
      "numbers": [
        13,
        21
      ],
      "room": "",
      "strings": [],
      "transform": "(best)",
      "unknown": [
        100,
        0,
        0,
        0,
        0,
        0,
        0,
        0,
        0,
        "N",
        0
      ],
      "x": 104,
      "y": 242
    },
    {
      "numbers": [
        14,
        17,
        20
      ],
      "room": "",
      "strings": [],
      "transform": "(best)",
      "unknown": [
        100,
        0,
        0,
        0,
        0,
        0,
        0,
        0,
        0,
        "N",
        0
      ],
      "x": 104,
      "y": 334
    },
    {
      "numbers": [
        16,
        15
      ],
      "room": "",
      "strings": [],
      "transform": "(best)",
      "unknown": [
        100,
        0,
        0,
        0,
        0,
        0,
        0,
        0,
        0,
        "N",
        0
      ],
      "x": 219,
      "y": 334
    },
    {
      "numbers": [
        21,
        19
      ],
      "room": "feature",
      "strings": [],
      "transform": "R90",
      "unknown": [
        100,
        0,
        0,
        0,
        0,
        0,
        0,
        0,
        0,
        "N",
        0
      ],
      "x": 35,
      "y": 242
    },
    {
      "numbers": [
        17
      ],
      "room": "vault2",
      "strings": [
        "unique2"
      ],
      "transform": "(best)",
      "unknown": [
        100,
        0,
        0,
        0,
        0,
        0,
        0,
        0,
        0,
        "N",
        0
      ],
      "x": 104,
      "y": 380
    },
    {
      "numbers": [
        19,
        20,
        23
      ],
      "room": "",
      "strings": [],
      "transform": "(best)",
      "unknown": [
        100,
        0,
        0,
        0,
        0,
        0,
        0,
        0,
        0,
        "N",
        0
      ],
      "x": 58,
      "y": 334
    },
    {
      "numbers": [
        22
      ],
      "room": "vault1",
      "strings": [
        "unique1"
      ],
      "transform": "(best)",
      "unknown": [
        100,
        0,
        0,
        0,
        0,
        0,
        0,
        0,
        0,
        "N",
        0
      ],
      "x": 219,
      "y": 219
    },
    {
      "numbers": [
        23
      ],
      "room": "vault2",
      "strings": [
        "unique2"
      ],
      "transform": "(best)",
      "unknown": [
        100,
        0,
        0,
        0,
        0,
        0,
        0,
        0,
        0,
        "N",
        0
      ],
      "x": 58,
      "y": 357
    },
    {
      "numbers": [
        24
      ],
      "room": "",
      "strings": [],
      "transform": "(best)",
      "unknown": [
        100,
        0,
        0,
        0,
        0,
        0,
        0,
        0,
        0,
        "V",
        0
      ],
      "x": 219,
      "y": 35
    },
    {
      "numbers": [
        25,
        24
      ],
      "room": "",
      "strings": [],
      "transform": "(best)",
      "unknown": [
        100,
        0,
        0,
        0,
        0,
        0,
        0,
        0,
        0,
        "V",
        0
      ],
      "x": 265,
      "y": 35
    },
    {
      "numbers": [
        25,
        26
      ],
      "room": "",
      "strings": [],
      "transform": "(best)",
      "unknown": [
        100,
        0,
        0,
        0,
        0,
        0,
        0,
        0,
        0,
        "V",
        0
      ],
      "x": 265,
      "y": 81
    },
    {
      "numbers": [
        43,
        26
      ],
      "room": "",
      "strings": [],
      "transform": "(best)",
      "unknown": [
        100,
        0,
        0,
        0,
        0,
        0,
        0,
        0,
        0,
        "V",
        0
      ],
      "x": 288,
      "y": 81
    },
    {
      "numbers": [
        27,
        44
      ],
      "room": "",
      "strings": [],
      "transform": "(best)",
      "unknown": [
        100,
        0,
        0,
        0,
        0,
        0,
        0,
        0,
        0,
        "V",
        0
      ],
      "x": 265,
      "y": 196
    },
    {
      "numbers": [
        28,
        29
      ],
      "room": "",
      "strings": [],
      "transform": "(best)",
      "unknown": [
        100,
        0,
        0,
        0,
        0,
        0,
        0,
        0,
        0,
        "V",
        0
      ],
      "x": 242,
      "y": 219
    },
    {
      "numbers": [
        29
      ],
      "room": "",
      "strings": [],
      "transform": "(best)",
      "unknown": [
        100,
        0,
        0,
        0,
        0,
        0,
        0,
        0,
        0,
        "V",
        0
      ],
      "x": 242,
      "y": 242
    },
    {
      "numbers": [
        30
      ],
      "room": "",
      "strings": [],
      "transform": "(best)",
      "unknown": [
        100,
        0,
        0,
        0,
        0,
        0,
        0,
        0,
        0,
        "V",
        0
      ],
      "x": 127,
      "y": 35
    },
    {
      "numbers": [
        30,
        31
      ],
      "room": "",
      "strings": [],
      "transform": "(best)",
      "unknown": [
        100,
        0,
        0,
        0,
        0,
        0,
        0,
        0,
        0,
        "V",
        0
      ],
      "x": 81,
      "y": 35
    },
    {
      "numbers": [
        31,
        32
      ],
      "room": "",
      "strings": [],
      "transform": "(best)",
      "unknown": [
        100,
        0,
        0,
        0,
        0,
        0,
        0,
        0,
        0,
        "V",
        0
      ],
      "x": 81,
      "y": 81
    },
    {
      "numbers": [
        32,
        33
      ],
      "room": "",
      "strings": [],
      "transform": "(best)",
      "unknown": [
        100,
        0,
        0,
        0,
        0,
        0,
        0,
        0,
        0,
        "V",
        0
      ],
      "x": 58,
      "y": 81
    },
    {
      "numbers": [
        33,
        34
      ],
      "room": "",
      "strings": [],
      "transform": "(best)",
      "unknown": [
        100,
        0,
        0,
        0,
        0,
        0,
        0,
        0,
        0,
        "V",
        0
      ],
      "x": 58,
      "y": 173
    },
    {
      "numbers": [
        34,
        35
      ],
      "room": "",
      "strings": [],
      "transform": "(best)",
      "unknown": [
        100,
        0,
        0,
        0,
        0,
        0,
        0,
        0,
        0,
        "V",
        0
      ],
      "x": 35,
      "y": 173
    },
    {
      "numbers": [
        35,
        42
      ],
      "room": "",
      "strings": [],
      "transform": "(best)",
      "unknown": [
        100,
        0,
        0,
        0,
        0,
        0,
        0,
        0,
        0,
        "V",
        0
      ],
      "x": 35,
      "y": 196
    },
    {
      "numbers": [
        40,
        39
      ],
      "room": "",
      "strings": [],
      "transform": "(best)",
      "unknown": [
        100,
        0,
        0,
        0,
        0,
        0,
        0,
        0,
        0,
        "V",
        0
      ],
      "x": 219,
      "y": 380
    },
    {
      "numbers": [
        36,
        48
      ],
      "room": "",
      "strings": [],
      "transform": "(best)",
      "unknown": [
        100,
        0,
        0,
        0,
        0,
        0,
        0,
        0,
        0,
        "V",
        0
      ],
      "x": 81,
      "y": 380
    },
    {
      "numbers": [
        37,
        38
      ],
      "room": "",
      "strings": [],
      "transform": "(best)",
      "unknown": [
        100,
        0,
        0,
        0,
        0,
        0,
        0,
        0,
        0,
        "V",
        0
      ],
      "x": 35,
      "y": 357
    },
    {
      "numbers": [
        46,
        38
      ],
      "room": "",
      "strings": [],
      "transform": "(best)",
      "unknown": [
        100,
        0,
        0,
        0,
        0,
        0,
        0,
        0,
        0,
        "V",
        0
      ],
      "x": 12,
      "y": 357
    },
    {
      "numbers": [
        39,
        47
      ],
      "room": "",
      "strings": [],
      "transform": "(best)",
      "unknown": [
        100,
        0,
        0,
        0,
        0,
        0,
        0,
        0,
        0,
        "V",
        0
      ],
      "x": 219,
      "y": 403
    },
    {
      "numbers": [
        41,
        40
      ],
      "room": "",
      "strings": [],
      "transform": "(best)",
      "unknown": [
        100,
        0,
        0,
        0,
        0,
        0,
        0,
        0,
        0,
        "V",
        0
      ],
      "x": 265,
      "y": 380
    },
    {
      "numbers": [
        41
      ],
      "room": "",
      "strings": [],
      "transform": "(best)",
      "unknown": [
        100,
        0,
        0,
        0,
        0,
        0,
        0,
        0,
        0,
        "V",
        0
      ],
      "x": 265,
      "y": 334
    },
    {
      "numbers": [
        42,
        45
      ],
      "room": "",
      "strings": [],
      "transform": "(best)",
      "unknown": [
        100,
        0,
        0,
        0,
        0,
        0,
        0,
        0,
        0,
        "V",
        0
      ],
      "x": 12,
      "y": 196
    },
    {
      "numbers": [
        43,
        27
      ],
      "room": "",
      "strings": [],
      "transform": "(best)",
      "unknown": [
        100,
        0,
        0,
        0,
        0,
        0,
        0,
        0,
        0,
        "V",
        0
      ],
      "x": 288,
      "y": 193
    },
    {
      "numbers": [
        44,
        28
      ],
      "room": "",
      "strings": [],
      "transform": "(best)",
      "unknown": [
        100,
        0,
        0,
        0,
        0,
        0,
        0,
        0,
        0,
        "V",
        0
      ],
      "x": 267,
      "y": 219
    },
    {
      "numbers": [
        45
      ],
      "room": "",
      "strings": [],
      "transform": "(best)",
      "unknown": [
        100,
        0,
        0,
        0,
        0,
        0,
        0,
        0,
        0,
        "V",
        0
      ],
      "x": 12,
      "y": 219
    },
    {
      "numbers": [
        46
      ],
      "room": "",
      "strings": [],
      "transform": "(best)",
      "unknown": [
        100,
        0,
        0,
        0,
        0,
        0,
        0,
        0,
        0,
        "V",
        0
      ],
      "x": 12,
      "y": 334
    },
    {
      "numbers": [
        36,
        47
      ],
      "room": "",
      "strings": [],
      "transform": "(best)",
      "unknown": [
        100,
        0,
        0,
        0,
        0,
        0,
        0,
        0,
        0,
        "V",
        0
      ],
      "x": 81,
      "y": 403
    },
    {
      "numbers": [
        37,
        48
      ],
      "room": "",
      "strings": [],
      "transform": "(best)",
      "unknown": [
        100,
        0,
        0,
        0,
        0,
        0,
        0,
        0,
        0,
        "V",
        0
      ],
      "x": 35,
      "y": 380
    }
  ],
  "room_set": [
    {
      "file": "Metadata/Terrain/Gallows/Act4_Interlude/Part3/P3_7/Rooms/Unique/Boss_01.arm",
      "prefix": null,
      "suffix": null,
      "tile_tag": null,
      "room_tag": "boss",
      "tile_tgt": null,
      "tile_parent": null
    },
    {
      "file": "Metadata/Terrain/Gallows/Act4_Interlude/Part3/P3_7/Rooms/Unique/Entrance_01.arm",
      "prefix": null,
      "suffix": null,
      "tile_tag": null,
      "room_tag": "entrance",
      "tile_tgt": null,
      "tile_parent": null
    },
    {
      "file": "Metadata/Terrain/Gallows/Act4_Interlude/Part3/P3_7/Rooms/Unique/Landmark_Vault_01.arm",
      "prefix": null,
      "suffix": null,
      "tile_tag": null,
      "room_tag": "vault1",
      "tile_tgt": null,
      "tile_parent": null
    },
    {
      "file": "Metadata/Terrain/Gallows/Act4_Interlude/Part3/P3_7/Rooms/Unique/Landmark_Vault_02.arm",
      "prefix": null,
      "suffix": null,
      "tile_tag": null,
      "room_tag": "vault2",
      "tile_tgt": null,
      "tile_parent": null
    },
    {
      "file": "Metadata/Terrain/Gallows/Act4_Interlude/Part3/P3_7/Rooms/Unique/Mission_01.arm",
      "prefix": null,
      "suffix": null,
      "tile_tag": null,
      "room_tag": "mission",
      "tile_tgt": null,
      "tile_parent": null
    },
    {
      "file": "Metadata/Terrain/Gallows/Act4_Interlude/Part3/P3_7/Rooms/Corridors/Bedroom_01.arm",
      "prefix": null,
      "suffix": null,
      "tile_tag": null,
      "room_tag": null,
      "tile_tgt": null,
      "tile_parent": null
    },
    {
      "file": "Metadata/Terrain/Gallows/Act4_Interlude/Part3/P3_7/Rooms/Corridors/Bedroom_02.arm",
      "prefix": null,
      "suffix": null,
      "tile_tag": null,
      "room_tag": null,
      "tile_tgt": null,
      "tile_parent": null
    },
    {
      "file": "Metadata/Terrain/Gallows/Act4_Interlude/Part3/P3_7/Rooms/Corridors/Bedroom_03.arm",
      "prefix": null,
      "suffix": null,
      "tile_tag": null,
      "room_tag": null,
      "tile_tgt": null,
      "tile_parent": null
    },
    {
      "file": "Metadata/Terrain/Gallows/Act4_Interlude/Part3/P3_7/Rooms/Corridors/Bedroom_04.arm",
      "prefix": null,
      "suffix": null,
      "tile_tag": null,
      "room_tag": null,
      "tile_tgt": null,
      "tile_parent": null
    },
    {
      "file": "Metadata/Terrain/Gallows/Act4_Interlude/Part3/P3_7/Rooms/Corridors/Office_01.arm",
      "prefix": null,
      "suffix": null,
      "tile_tag": null,
      "room_tag": null,
      "tile_tgt": null,
      "tile_parent": null
    },
    {
      "file": "Metadata/Terrain/Gallows/Act4_Interlude/Part3/P3_7/Rooms/Corridors/Office_02.arm",
      "prefix": null,
      "suffix": null,
      "tile_tag": null,
      "room_tag": null,
      "tile_tgt": null,
      "tile_parent": null
    },
    {
      "file": "Metadata/Terrain/Gallows/Act4_Interlude/Part3/P3_7/Rooms/Corridors/Office_03.arm",
      "prefix": null,
      "suffix": null,
      "tile_tag": null,
      "room_tag": null,
      "tile_tgt": null,
      "tile_parent": null
    },
    {
      "file": "Metadata/Terrain/Gallows/Act4_Interlude/Part3/P3_7/Rooms/Corridors/Office_04.arm",
      "prefix": null,
      "suffix": null,
      "tile_tag": null,
      "room_tag": null,
      "tile_tgt": null,
      "tile_parent": null
    },
    {
      "file": "Metadata/Terrain/Gallows/Act4_Interlude/Part3/P3_7/Rooms/Corridors/Cc_01.arm",
      "prefix": null,
      "suffix": null,
      "tile_tag": null,
      "room_tag": null,
      "tile_tgt": null,
      "tile_parent": null
    },
    {
      "file": "Metadata/Terrain/Gallows/Act4_Interlude/Part3/P3_7/Rooms/Corridors/Cc_02.arm",
      "prefix": null,
      "suffix": null,
      "tile_tag": null,
      "room_tag": null,
      "tile_tgt": null,
      "tile_parent": null
    },
    {
      "file": "Metadata/Terrain/Gallows/Act4_Interlude/Part3/P3_7/Rooms/Corridors/Cc_03.arm",
      "prefix": null,
      "suffix": null,
      "tile_tag": null,
      "room_tag": null,
      "tile_tgt": null,
      "tile_parent": null
    },
    {
      "file": "Metadata/Terrain/Gallows/Act4_Interlude/Part3/P3_7/Rooms/Corridors/Cc_04.arm",
      "prefix": null,
      "suffix": null,
      "tile_tag": null,
      "room_tag": null,
      "tile_tgt": null,
      "tile_parent": null
    },
    {
      "file": "Metadata/Terrain/Gallows/Act4_Interlude/Part3/P3_7/Rooms/Corridors/St_01.arm",
      "prefix": null,
      "suffix": null,
      "tile_tag": null,
      "room_tag": null,
      "tile_tgt": null,
      "tile_parent": null
    },
    {
      "file": "Metadata/Terrain/Gallows/Act4_Interlude/Part3/P3_7/Rooms/Corridors/St_02.arm",
      "prefix": null,
      "suffix": null,
      "tile_tag": null,
      "room_tag": null,
      "tile_tgt": null,
      "tile_parent": null
    },
    {
      "file": "Metadata/Terrain/Gallows/Act4_Interlude/Part3/P3_7/Rooms/Corridors/St_03.arm",
      "prefix": null,
      "suffix": null,
      "tile_tag": null,
      "room_tag": null,
      "tile_tgt": null,
      "tile_parent": null
    },
    {
      "file": "Metadata/Terrain/Gallows/Act4_Interlude/Part3/P3_7/Rooms/Corridors/St_04.arm",
      "prefix": null,
      "suffix": null,
      "tile_tag": null,
      "room_tag": null,
      "tile_tgt": null,
      "tile_parent": null
    },
    {
      "file": "Metadata/Terrain/Gallows/Act4_Interlude/Part3/P3_7/Rooms/Corridors/Tri_01.arm",
      "prefix": null,
      "suffix": null,
      "tile_tag": null,
      "room_tag": null,
      "tile_tgt": null,
      "tile_parent": null
    },
    {
      "file": "Metadata/Terrain/Gallows/Act4_Interlude/Part3/P3_7/Rooms/Corridors/Tri_02.arm",
      "prefix": null,
      "suffix": null,
      "tile_tag": null,
      "room_tag": null,
      "tile_tgt": null,
      "tile_parent": null
    },
    {
      "file": "Metadata/Terrain/Gallows/Act4_Interlude/Part3/P3_7/Rooms/Corridors/Tri_03.arm",
      "prefix": null,
      "suffix": null,
      "tile_tag": null,
      "room_tag": null,
      "tile_tgt": null,
      "tile_parent": null
    },
    {
      "file": "Metadata/Terrain/Gallows/Act4_Interlude/Part3/P3_7/Rooms/Corridors/Tri_04.arm",
      "prefix": null,
      "suffix": null,
      "tile_tag": null,
      "room_tag": null,
      "tile_tgt": null,
      "tile_parent": null
    },
    {
      "file": "Metadata/Terrain/Gallows/Act4_Interlude/Part3/P3_7/Rooms/Corridors/X_01.arm",
      "prefix": null,
      "suffix": null,
      "tile_tag": null,
      "room_tag": null,
      "tile_tgt": null,
      "tile_parent": null
    },
    {
      "file": "Metadata/Terrain/Gallows/Act4_Interlude/Part3/P3_7/Rooms/Corridors/X_02.arm",
      "prefix": null,
      "suffix": null,
      "tile_tag": null,
      "room_tag": null,
      "tile_tgt": null,
      "tile_parent": null
    },
    {
      "file": "Metadata/Terrain/Gallows/Act4_Interlude/Part3/P3_7/Rooms/Corridors/X_03.arm",
      "prefix": null,
      "suffix": null,
      "tile_tag": null,
      "room_tag": null,
      "tile_tgt": null,
      "tile_parent": null
    },
    {
      "file": "Metadata/Terrain/Gallows/Act4_Interlude/Part3/P3_7/Rooms/Corridors/X_04.arm",
      "prefix": null,
      "suffix": null,
      "tile_tag": null,
      "room_tag": null,
      "tile_tgt": null,
      "tile_parent": null
    },
    {
      "file": "Metadata/Terrain/Gallows/Act4_Interlude/Part3/P3_7/Rooms/Library/LibraryH_4open_01.arm",
      "prefix": [
        "20"
      ],
      "suffix": null,
      "tile_tag": null,
      "room_tag": "feature",
      "tile_tgt": null,
      "tile_parent": null
    },
    {
      "file": "Metadata/Terrain/Gallows/Act4_Interlude/Part3/P3_7/Rooms/Library/LibraryH_4open_02.arm",
      "prefix": [
        "20"
      ],
      "suffix": null,
      "tile_tag": null,
      "room_tag": "feature",
      "tile_tgt": null,
      "tile_parent": null
    },
    {
      "file": "Metadata/Terrain/Gallows/Act4_Interlude/Part3/P3_7/Rooms/Library/LibraryH_4open_03.arm",
      "prefix": [
        "20"
      ],
      "suffix": null,
      "tile_tag": null,
      "room_tag": "feature",
      "tile_tgt": null,
      "tile_parent": null
    },
    {
      "file": "Metadata/Terrain/Gallows/Act4_Interlude/Part3/P3_7/Rooms/Library/LibraryH_4open_04.arm",
      "prefix": [
        "20"
      ],
      "suffix": null,
      "tile_tag": null,
      "room_tag": "feature",
      "tile_tgt": null,
      "tile_parent": null
    },
    {
      "file": "Metadata/Terrain/Gallows/Act4_Interlude/Part3/P3_7/Rooms/Library/LibraryV_4open_01.arm",
      "prefix": [
        "20"
      ],
      "suffix": null,
      "tile_tag": null,
      "room_tag": "feature",
      "tile_tgt": null,
      "tile_parent": null
    },
    {
      "file": "Metadata/Terrain/Gallows/Act4_Interlude/Part3/P3_7/Rooms/Library/LibraryV_4open_02.arm",
      "prefix": [
        "20"
      ],
      "suffix": null,
      "tile_tag": null,
      "room_tag": "feature",
      "tile_tgt": null,
      "tile_parent": null
    },
    {
      "file": "Metadata/Terrain/Gallows/Act4_Interlude/Part3/P3_7/Rooms/Library/LibraryV_4open_03.arm",
      "prefix": [
        "20"
      ],
      "suffix": null,
      "tile_tag": null,
      "room_tag": "feature",
      "tile_tgt": null,
      "tile_parent": null
    },
    {
      "file": "Metadata/Terrain/Gallows/Act4_Interlude/Part3/P3_7/Rooms/Library/LibraryV_4open_04.arm",
      "prefix": [
        "20"
      ],
      "suffix": null,
      "tile_tag": null,
      "room_tag": "feature",
      "tile_tgt": null,
      "tile_parent": null
    }
  ],
  "size": [
    16,
    18
  ],
  "strings": [
    "",
    "",
    ""
  ],
  "tile_set": [
    {
      "file": "Metadata/Terrain/Dungeon/NextFeatures/dungeon_blank_fill.tdt",
      "prefix": null,
      "suffix": null,
      "tile_tag": null,
      "room_tag": null,
      "tile_tgt": "Art/Models/Terrain/Jungle/Tiles/VaalInterior/dungeon_blank_fill.tgt",
      "tile_parent": null
    },
    {
      "file": "Metadata/Terrain/Dungeon/NextFeatures/dungeon_blank_fill_forced.tdt",
      "prefix": null,
      "suffix": null,
      "tile_tag": "forcedblank",
      "room_tag": null,
      "tile_tgt": "Art/Models/Terrain/Jungle/Tiles/VaalInterior/dungeon_blank_fill.tgt",
      "tile_parent": null
    },
    {
      "file": "Metadata/Terrain/Dungeon/black.tdt",
      "prefix": [
        "//"
      ],
      "suffix": null,
      "tile_tag": null,
      "room_tag": null,
      "tile_tgt": null,
      "tile_parent": null
    },
    {
      "file": "Metadata/Terrain/forced_blank.tdt",
      "prefix": [
        "//"
      ],
      "suffix": null,
      "tile_tag": null,
      "room_tag": null,
      "tile_tgt": null,
      "tile_parent": null
    },
    {
      "file": "Metadata/Terrain/Dungeon/NextFeatures/forced_blank_alt.tdt",
      "prefix": null,
      "suffix": null,
      "tile_tag": "forcedblank_alt",
      "room_tag": null,
      "tile_tgt": "Art/Models/Terrain/ForcedBlank.tgt",
      "tile_parent": null
    },
    {
      "file": "Metadata/Terrain/Interlude/Part3/P3_7/Vault_Entrance.tdt",
      "prefix": null,
      "suffix": null,
      "tile_tag": "entrance",
      "room_tag": null,
      "tile_tgt": "Art/Models/Terrain/Interlude/Part3/P3_7/Vault_Entrance.tgt",
      "tile_parent": null
    },
    {
      "file": "Metadata/Terrain/Interlude/Part3/P3_7/BloodVault_Bossroom.tdt",
      "prefix": null,
      "suffix": null,
      "tile_tag": "boss",
      "room_tag": null,
      "tile_tgt": "Art/Models/Terrain/Interlude/Part3/P3_7/BloodVault_Bossroom.tgt",
      "tile_parent": null
    },
    {
      "file": "Metadata/Terrain/Interlude/Part3/P3_7/dungeon_door_thin_key.tdt",
      "prefix": null,
      "suffix": null,
      "tile_tag": "door_key",
      "room_tag": null,
      "tile_tgt": null,
      "tile_parent": {
        "file": "Metadata/Terrain/Dungeon/NextFeatures/dungeon_entrance_thin_v01_01.tdt",
        "tile_parent": null,
        "tile_tag": "door",
        "tile_tgt": "Art/Models/Terrain/Jungle/Tiles/VaalInterior/dungeon_entrance_thin_v01_01.tgt"
      }
    },
    {
      "file": "Metadata/Terrain/Interlude/Part3/P3_7/dungeon_LifePod_01.tdt",
      "prefix": null,
      "suffix": null,
      "tile_tag": "lifepod",
      "room_tag": null,
      "tile_tgt": "Art/Models/Terrain/Interlude/Part3/P3_7/dungeon_LifePod_01.tgt",
      "tile_parent": null
    },
    {
      "file": "Metadata/Terrain/Interlude/Part3/P3_7/VaultThickChestSt_01magic.tdt",
      "prefix": null,
      "suffix": null,
      "tile_tag": "vault_chest_magic",
      "room_tag": null,
      "tile_tgt": "Art/Models/Terrain/Jungle/Tiles/TreasureVault/Present/VaultThickChestSt_01.tgt",
      "tile_parent": null
    },
    {
      "file": "Metadata/Terrain/Interlude/Part3/P3_7/VaultThickDownscreenNoChestSt_01magic.tdt",
      "prefix": null,
      "suffix": null,
      "tile_tag": "vault_chest_magic",
      "room_tag": null,
      "tile_tgt": "Art/Models/Terrain/Jungle/Tiles/TreasureVault/Present/VaultThickSt_01.tgt",
      "tile_parent": null
    },
    {
      "file": "Metadata/Terrain/Interlude/Part3/P3_7/VaultThickChestSt_01rare.tdt",
      "prefix": null,
      "suffix": null,
      "tile_tag": "vault_chest_rare",
      "room_tag": null,
      "tile_tgt": "Art/Models/Terrain/Jungle/Tiles/TreasureVault/Present/VaultThickChestSt_01.tgt",
      "tile_parent": null
    },
    {
      "file": "Metadata/Terrain/Interlude/Part3/P3_7/VaultThickDownscreenNoChestSt_01rare.tdt",
      "prefix": null,
      "suffix": null,
      "tile_tag": "vault_chest_rare",
      "room_tag": null,
      "tile_tgt": "Art/Models/Terrain/Jungle/Tiles/TreasureVault/Present/VaultThickSt_01.tgt",
      "tile_parent": null
    },
    {
      "file": "Metadata/Terrain/Dungeon/NextFeatures/RoofShadow7x7_01.tdt",
      "prefix": null,
      "suffix": null,
      "tile_tag": "roof_light",
      "room_tag": null,
      "tile_tgt": "Art/Models/Terrain/Jungle/Tiles/TreasureVault/Past/RoofShadow7x7_01.tgt",
      "tile_parent": null
    },
    {
      "file": "Metadata/Terrain/Dungeon/NextFeatures/ThickwallConcave_Round_01_feature.tdt",
      "prefix": null,
      "suffix": null,
      "tile_tag": "curve",
      "room_tag": null,
      "tile_tgt": "Art/Models/Terrain/Jungle/Tiles/Observatorium/ThickwallConcave_Round_01.tgt",
      "tile_parent": null
    },
    {
      "file": "Metadata/Terrain/Dungeon/NextFeatures/dungeon_DoorThickWall_01.tdt",
      "prefix": null,
      "suffix": null,
      "tile_tag": "door_facade",
      "room_tag": null,
      "tile_tgt": "Art/Models/Terrain/Jungle/Tiles/VaalInterior/dungeon_DoorThickWall_01.tgt",
      "tile_parent": null
    },
    {
      "file": "Metadata/Terrain/Dungeon/NextFeatures/dungeon_column_v01_01.tdt",
      "prefix": null,
      "suffix": null,
      "tile_tag": "column",
      "room_tag": null,
      "tile_tgt": "Art/Models/Terrain/Jungle/Tiles/VaalInterior/dungeon_column_v01_01.tgt",
      "tile_parent": null
    },
    {
      "file": "Metadata/Terrain/Dungeon/NextFeatures/dungeon_entrance_thin_v01_01.tdt",
      "prefix": null,
      "suffix": null,
      "tile_tag": "door",
      "room_tag": null,
      "tile_tgt": "Art/Models/Terrain/Jungle/Tiles/VaalInterior/dungeon_entrance_thin_v01_01.tgt",
      "tile_parent": null
    },
    {
      "file": "Metadata/Terrain/Dungeon/NextFeatures/dungeon_thick_wall_pillar_v01_01.tdt",
      "prefix": null,
      "suffix": null,
      "tile_tag": "column",
      "room_tag": null,
      "tile_tgt": "Art/Models/Terrain/Jungle/Tiles/VaalInterior/dungeon_thick_wall_pillar_v01_01.tgt",
      "tile_parent": null
    },
    {
      "file": "Metadata/Terrain/Dungeon/NextFeatures/dungeon_entrance_thick_v04_01.tdt",
      "prefix": null,
      "suffix": null,
      "tile_tag": "halldoorway",
      "room_tag": null,
      "tile_tgt": "Art/Models/Terrain/Jungle/Tiles/VaalInterior/dungeon_entrance_thick_v04_01.tgt",
      "tile_parent": null
    },
    {
      "file": "Metadata/Terrain/Dungeon/NextFeatures/dungeon_entrance_thick_v04_DoorBack_Cc_01.tdt",
      "prefix": null,
      "suffix": null,
      "tile_tag": null,
      "room_tag": null,
      "tile_tgt": "Art/Models/Terrain/Jungle/Tiles/VaalInterior/DoorBack_Cv_01.tgt",
      "tile_parent": null
    },
    {
      "file": "Metadata/Terrain/Dungeon/NextFeatures/dungeon_entrance_thick_v04_DoorBack_St_01.tdt",
      "prefix": null,
      "suffix": null,
      "tile_tag": null,
      "room_tag": null,
      "tile_tgt": "Art/Models/Terrain/Jungle/Tiles/VaalInterior/DoorBack_Cv_01.tgt",
      "tile_parent": null
    },
    {
      "file": "Metadata/Terrain/Dungeon/NextFeatures/dungeon_blank_MachinariumStorageDummy.tdt",
      "prefix": null,
      "suffix": null,
      "tile_tag": "StorageOverlayMarker",
      "room_tag": null,
      "tile_tgt": "Art/Models/Terrain/Jungle/Tiles/VaalInterior/dungeon_blank_fill.tgt",
      "tile_parent": null
    },
    {
      "file": "Metadata/Terrain/Dungeon/NextLedge/dungeon_floorwall_thin_height_v01_01.tdt",
      "prefix": null,
      "suffix": null,
      "tile_tag": null,
      "room_tag": null,
      "tile_tgt": "Art/Models/Terrain/Jungle/Tiles/VaalInterior/dungeon_floorwall_thin_height_v01_01.tgt",
      "tile_parent": null
    },
    {
      "file": "Metadata/Terrain/Dungeon/NextLedge/dungeon_floor_height_corner_convex_v01_01.tdt",
      "prefix": null,
      "suffix": null,
      "tile_tag": null,
      "room_tag": null,
      "tile_tgt": "Art/Models/Terrain/Jungle/Tiles/VaalInterior/dungeon_floor_height_corner_convex_v01_01.tgt",
      "tile_parent": null
    },
    {
      "file": "Metadata/Terrain/Dungeon/NextLedge/dungeon_floor_height_corner_v01_01.tdt",
      "prefix": null,
      "suffix": null,
      "tile_tag": null,
      "room_tag": null,
      "tile_tgt": "Art/Models/Terrain/Jungle/Tiles/VaalInterior/dungeon_floor_height_corner_v01_01.tgt",
      "tile_parent": null
    },
    {
      "file": "Metadata/Terrain/Dungeon/NextLedge/dungeon_floor_height_v01_01.tdt",
      "prefix": null,
      "suffix": null,
      "tile_tag": "busted",
      "room_tag": null,
      "tile_tgt": "Art/Models/Terrain/Jungle/Tiles/VaalInterior/dungeon_floor_height_v01_01.tgt",
      "tile_parent": null
    },
    {
      "file": "Metadata/Terrain/Dungeon/NextLedge/dungeon_floor_height_v01_010.tdt",
      "prefix": null,
      "suffix": null,
      "tile_tag": null,
      "room_tag": null,
      "tile_tgt": "Art/Models/Terrain/Jungle/Tiles/VaalInterior/dungeon_floor_height_v01_010.tgt",
      "tile_parent": null
    },
    {
      "file": "Metadata/Terrain/Dungeon/NextLedge/dungeon_floor_height_v01_02.tdt",
      "prefix": null,
      "suffix": null,
      "tile_tag": null,
      "room_tag": null,
      "tile_tgt": "Art/Models/Terrain/Jungle/Tiles/VaalInterior/dungeon_floor_height_v01_02.tgt",
      "tile_parent": null
    },
    {
      "file": "Metadata/Terrain/Dungeon/NextLedge/dungeon_floor_height_v01_03.tdt",
      "prefix": null,
      "suffix": null,
      "tile_tag": null,
      "room_tag": null,
      "tile_tgt": "Art/Models/Terrain/Jungle/Tiles/VaalInterior/dungeon_floor_height_v01_03.tgt",
      "tile_parent": null
    },
    {
      "file": "Metadata/Terrain/Dungeon/NextLedge/dungeon_floor_height_v01_04.tdt",
      "prefix": null,
      "suffix": null,
      "tile_tag": null,
      "room_tag": null,
      "tile_tgt": "Art/Models/Terrain/Jungle/Tiles/VaalInterior/dungeon_floor_height_v01_04.tgt",
      "tile_parent": null
    },
    {
      "file": "Metadata/Terrain/Dungeon/NextLedge/dungeon_floor_height_v01_05.tdt",
      "prefix": null,
      "suffix": null,
      "tile_tag": null,
      "room_tag": null,
      "tile_tgt": "Art/Models/Terrain/Jungle/Tiles/VaalInterior/dungeon_floor_height_v01_05.tgt",
      "tile_parent": null
    },
    {
      "file": "Metadata/Terrain/Dungeon/NextLedge/dungeon_floor_height_v01_06.tdt",
      "prefix": null,
      "suffix": null,
      "tile_tag": null,
      "room_tag": null,
      "tile_tgt": "Art/Models/Terrain/Jungle/Tiles/VaalInterior/dungeon_floor_height_v01_06.tgt",
      "tile_parent": null
    },
    {
      "file": "Metadata/Terrain/Dungeon/NextLedge/dungeon_floor_height_v01_07.tdt",
      "prefix": null,
      "suffix": null,
      "tile_tag": null,
      "room_tag": null,
      "tile_tgt": "Art/Models/Terrain/Jungle/Tiles/VaalInterior/dungeon_floor_height_v01_07.tgt",
      "tile_parent": null
    },
    {
      "file": "Metadata/Terrain/Dungeon/NextLedge/dungeon_floor_height_v01_08.tdt",
      "prefix": null,
      "suffix": null,
      "tile_tag": null,
      "room_tag": null,
      "tile_tgt": "Art/Models/Terrain/Jungle/Tiles/VaalInterior/dungeon_floor_height_v01_08.tgt",
      "tile_parent": null
    },
    {
      "file": "Metadata/Terrain/Dungeon/NextLedge/dungeon_floor_height_v01_09.tdt",
      "prefix": null,
      "suffix": null,
      "tile_tag": null,
      "room_tag": null,
      "tile_tgt": "Art/Models/Terrain/Jungle/Tiles/VaalInterior/dungeon_floor_height_v01_09.tgt",
      "tile_parent": null
    },
    {
      "file": "Metadata/Terrain/Dungeon/NextLedge/dungeon_stairs_fill_v01_01.tdt",
      "prefix": null,
      "suffix": null,
      "tile_tag": null,
      "room_tag": null,
      "tile_tgt": "Art/Models/Terrain/Jungle/Tiles/VaalInterior/dungeon_stairs_fill_v01_01.tgt",
      "tile_parent": null
    },
    {
      "file": "Metadata/Terrain/Dungeon/NextLedge/dungeon_stairs_fill_v01_02.tdt",
      "prefix": null,
      "suffix": null,
      "tile_tag": null,
      "room_tag": null,
      "tile_tgt": "Art/Models/Terrain/Jungle/Tiles/VaalInterior/dungeon_stairs_fill_v01_02.tgt",
      "tile_parent": null
    },
    {
      "file": "Metadata/Terrain/Dungeon/NextLedge/dungeon_stairs_fill_v01_03.tdt",
      "prefix": null,
      "suffix": null,
      "tile_tag": null,
      "room_tag": null,
      "tile_tgt": "Art/Models/Terrain/Jungle/Tiles/VaalInterior/dungeon_stairs_fill_v01_03.tgt",
      "tile_parent": null
    },
    {
      "file": "Metadata/Terrain/Dungeon/NextLedge/dungeon_wall_height_v01_01.tdt",
      "prefix": null,
      "suffix": null,
      "tile_tag": null,
      "room_tag": null,
      "tile_tgt": "Art/Models/Terrain/Jungle/Tiles/VaalInterior/dungeon_wall_height_v01_01.tgt",
      "tile_parent": null
    },
    {
      "file": "Metadata/Terrain/Dungeon/NextLedge/dungeon_wall_thin_height_v01_01.tdt",
      "prefix": null,
      "suffix": null,
      "tile_tag": null,
      "room_tag": null,
      "tile_tgt": "Art/Models/Terrain/Jungle/Tiles/VaalInterior/dungeon_wall_thin_height_v01_01.tgt",
      "tile_parent": null
    },
    {
      "file": "Metadata/Terrain/Dungeon/NextLedge/dungeon_wall_thin_height_v01_02.tdt",
      "prefix": null,
      "suffix": null,
      "tile_tag": null,
      "room_tag": null,
      "tile_tgt": "Art/Models/Terrain/Jungle/Tiles/VaalInterior/dungeon_wall_thin_height_v01_02.tgt",
      "tile_parent": null
    },
    {
      "file": "Metadata/Terrain/Dungeon/NextLedge/dungeon_wall_thin_height_v02_01.tdt",
      "prefix": null,
      "suffix": null,
      "tile_tag": null,
      "room_tag": null,
      "tile_tgt": "Art/Models/Terrain/Jungle/Tiles/VaalInterior/dungeon_wall_thin_height_v02_01.tgt",
      "tile_parent": null
    },
    {
      "file": "Metadata/Terrain/Dungeon/NextStairs/Circle_stairs_01.tdt",
      "prefix": null,
      "suffix": null,
      "tile_tag": null,
      "room_tag": null,
      "tile_tgt": "Art/Models/Terrain/Jungle/Tiles/Observatorium/Circle_stair_01.tgt",
      "tile_parent": null
    },
    {
      "file": "Metadata/Terrain/Dungeon/NextStairs/dungeon_floor_height_concave_stairs_v01_01.tdt",
      "prefix": null,
      "suffix": null,
      "tile_tag": null,
      "room_tag": null,
      "tile_tgt": "Art/Models/Terrain/Jungle/Tiles/VaalInterior/dungeon_floor_height_concave_stairs_v01_01.tgt",
      "tile_parent": null
    },
    {
      "file": "Metadata/Terrain/Dungeon/NextStairs/dungeon_floor_height_convex_stairs_v01_02.tdt",
      "prefix": null,
      "suffix": null,
      "tile_tag": null,
      "room_tag": null,
      "tile_tgt": "Art/Models/Terrain/Jungle/Tiles/VaalInterior/dungeon_floor_height_convex_stairs_v01_02.tgt",
      "tile_parent": null
    },
    {
      "file": "Metadata/Terrain/Dungeon/NextStairs/dungeon_half_stairs_v01_01.tdt",
      "prefix": null,
      "suffix": null,
      "tile_tag": null,
      "room_tag": null,
      "tile_tgt": "Art/Models/Terrain/Jungle/Tiles/VaalInterior/dungeon_half_stairs_v01_01.tgt",
      "tile_parent": null
    },
    {
      "file": "Metadata/Terrain/Dungeon/NextStairs/dungeon_stairs_concave_v01_01.tdt",
      "prefix": null,
      "suffix": null,
      "tile_tag": null,
      "room_tag": null,
      "tile_tgt": "Art/Models/Terrain/Jungle/Tiles/VaalInterior/dungeon_stairs_concave_v01_01.tgt",
      "tile_parent": null
    },
    {
      "file": "Metadata/Terrain/Dungeon/NextStairs/dungeon_stairs_convex_v01_01.tdt",
      "prefix": null,
      "suffix": null,
      "tile_tag": null,
      "room_tag": null,
      "tile_tgt": "Art/Models/Terrain/Jungle/Tiles/VaalInterior/dungeon_stairs_convex_v01_01.tgt",
      "tile_parent": null
    },
    {
      "file": "Metadata/Terrain/Dungeon/NextStairs/dungeon_stairs_straight_v01_01.tdt",
      "prefix": null,
      "suffix": null,
      "tile_tag": "stairs",
      "room_tag": null,
      "tile_tgt": "Art/Models/Terrain/Jungle/Tiles/VaalInterior/dungeon_stairs_straight_v01_01.tgt",
      "tile_parent": null
    },
    {
      "file": "Metadata/Terrain/Dungeon/NextStairs/dungeon_stairs_straight_v02_02.tdt",
      "prefix": null,
      "suffix": null,
      "tile_tag": null,
      "room_tag": null,
      "tile_tgt": "Art/Models/Terrain/Jungle/Tiles/VaalInterior/dungeon_stairs_straight_v02_02.tgt",
      "tile_parent": null
    },
    {
      "file": "Metadata/Terrain/Dungeon/NextStairs/dungeon_stairs_straight_v03_01.tdt",
      "prefix": null,
      "suffix": null,
      "tile_tag": null,
      "room_tag": null,
      "tile_tgt": "Art/Models/Terrain/Jungle/Tiles/VaalInterior/dungeon_stairs_straight_v03_01.tgt",
      "tile_parent": null
    },
    {
      "file": "Metadata/Terrain/Dungeon/NextStairs/dungeon_stairs_to_ledge_v01_01.tdt",
      "prefix": null,
      "suffix": null,
      "tile_tag": null,
      "room_tag": null,
      "tile_tgt": "Art/Models/Terrain/Jungle/Tiles/VaalInterior/dungeon_stairs_to_ledge_v01_01.tgt",
      "tile_parent": null
    },
    {
      "file": "Metadata/Terrain/Dungeon/NextStairs/dungeon_wall_straight_stairs_v01_01.tdt",
      "prefix": null,
      "suffix": null,
      "tile_tag": null,
      "room_tag": null,
      "tile_tgt": "Art/Models/Terrain/Jungle/Tiles/VaalInterior/dungeon_wall_straight_stairs_v01_01.tgt",
      "tile_parent": null
    },
    {
      "file": "Metadata/Terrain/Dungeon/NextStairs/dungeon_stairs_thin_straight_v01_01.tdt",
      "prefix": null,
      "suffix": null,
      "tile_tag": null,
      "room_tag": null,
      "tile_tgt": "Art/Models/Terrain/Jungle/Tiles/VaalInterior/dungeon_stairs_thin_straight_v01_01.tgt",
      "tile_parent": null
    },
    {
      "file": "Metadata/Terrain/Dungeon/NextWalls/dungeon_thick_to_thin_v01_01.tdt",
      "prefix": null,
      "suffix": null,
      "tile_tag": null,
      "room_tag": null,
      "tile_tgt": "Art/Models/Terrain/Jungle/Tiles/VaalInterior/dungeon_thick_to_thin_v01_01.tgt",
      "tile_parent": null
    },
    {
      "file": "Metadata/Terrain/Dungeon/NextWalls/dungeon_thick_to_thin_v01_02.tdt",
      "prefix": null,
      "suffix": null,
      "tile_tag": null,
      "room_tag": null,
      "tile_tgt": "Art/Models/Terrain/Jungle/Tiles/VaalInterior/dungeon_thick_to_thin_v01_02.tgt",
      "tile_parent": null
    },
    {
      "file": "Metadata/Terrain/Dungeon/NextWalls/dungeon_wall_corner_concave_v02_02.tdt",
      "prefix": null,
      "suffix": null,
      "tile_tag": null,
      "room_tag": null,
      "tile_tgt": "Art/Models/Terrain/Jungle/Tiles/VaalInterior/dungeon_wall_corner_concave_v02_02.tgt",
      "tile_parent": null
    },
    {
      "file": "Metadata/Terrain/Dungeon/NextWalls/dungeon_wall_corner_convex_v01_01.tdt",
      "prefix": null,
      "suffix": null,
      "tile_tag": null,
      "room_tag": null,
      "tile_tgt": "Art/Models/Terrain/Jungle/Tiles/VaalInterior/dungeon_wall_corner_convex_v01_01.tgt",
      "tile_parent": null
    },
    {
      "file": "Metadata/Terrain/Dungeon/NextWalls/dungeon_wall_straight_v01_01.tdt",
      "prefix": null,
      "suffix": null,
      "tile_tag": null,
      "room_tag": null,
      "tile_tgt": "Art/Models/Terrain/Jungle/Tiles/VaalInterior/dungeon_wall_straight_v01_01.tgt",
      "tile_parent": null
    },
    {
      "file": "Metadata/Terrain/Dungeon/NextWalls/dungeon_wall_straight_v01_02.tdt",
      "prefix": null,
      "suffix": null,
      "tile_tag": null,
      "room_tag": null,
      "tile_tgt": "Art/Models/Terrain/Jungle/Tiles/VaalInterior/dungeon_wall_straight_v01_02.tgt",
      "tile_parent": null
    },
    {
      "file": "Metadata/Terrain/Dungeon/NextWalls/dungeon_wall_straight_v01_03.tdt",
      "prefix": null,
      "suffix": null,
      "tile_tag": null,
      "room_tag": null,
      "tile_tgt": "Art/Models/Terrain/Jungle/Tiles/VaalInterior/dungeon_wall_straight_v01_03.tgt",
      "tile_parent": null
    },
    {
      "file": "Metadata/Terrain/Dungeon/NextWalls/dungeon_wall_straight_v02_01.tdt",
      "prefix": null,
      "suffix": null,
      "tile_tag": null,
      "room_tag": null,
      "tile_tgt": "Art/Models/Terrain/Jungle/Tiles/VaalInterior/dungeon_wall_straight_v02_01.tgt",
      "tile_parent": null
    },
    {
      "file": "Metadata/Terrain/Dungeon/NextWalls/dungeon_wall_straight_v02_02.tdt",
      "prefix": null,
      "suffix": null,
      "tile_tag": null,
      "room_tag": null,
      "tile_tgt": "Art/Models/Terrain/Jungle/Tiles/VaalInterior/dungeon_wall_straight_v02_02.tgt",
      "tile_parent": null
    },
    {
      "file": "Metadata/Terrain/Dungeon/NextWalls/dungeon_wall_straight_v03_01.tdt",
      "prefix": null,
      "suffix": null,
      "tile_tag": null,
      "room_tag": null,
      "tile_tgt": "Art/Models/Terrain/Jungle/Tiles/VaalInterior/dungeon_wall_straight_v03_01.tgt",
      "tile_parent": null
    },
    {
      "file": "Metadata/Terrain/Dungeon/NextWalls/dungeon_wall_straight_v04_01.tdt",
      "prefix": null,
      "suffix": null,
      "tile_tag": null,
      "room_tag": null,
      "tile_tgt": "Art/Models/Terrain/Jungle/Tiles/VaalInterior/dungeon_wall_straight_v04_01.tgt",
      "tile_parent": null
    },
    {
      "file": "Metadata/Terrain/Dungeon/NextWalls/dungeon_wall_thick_X_v01_01.tdt",
      "prefix": null,
      "suffix": null,
      "tile_tag": null,
      "room_tag": null,
      "tile_tgt": "Art/Models/Terrain/Jungle/Tiles/VaalInterior/dungeon_wall_thick_X_v01_01.tgt",
      "tile_parent": null
    },
    {
      "file": "Metadata/Terrain/Dungeon/NextWalls/dungeon_wall_thin_corner_v01_01.tdt",
      "prefix": null,
      "suffix": null,
      "tile_tag": null,
      "room_tag": null,
      "tile_tgt": "Art/Models/Terrain/Jungle/Tiles/VaalInterior/dungeon_wall_thin_corner_v01_01.tgt",
      "tile_parent": null
    },
    {
      "file": "Metadata/Terrain/Dungeon/NextWalls/dungeon_wall_thin_corner_v02_01.tdt",
      "prefix": null,
      "suffix": null,
      "tile_tag": null,
      "room_tag": null,
      "tile_tgt": "Art/Models/Terrain/Jungle/Tiles/VaalInterior/dungeon_wall_thin_corner_v02_01.tgt",
      "tile_parent": null
    },
    {
      "file": "Metadata/Terrain/Dungeon/NextWalls/dungeon_wall_thin_end_v01_01.tdt",
      "prefix": null,
      "suffix": null,
      "tile_tag": null,
      "room_tag": null,
      "tile_tgt": "Art/Models/Terrain/Jungle/Tiles/VaalInterior/dungeon_wall_thin_end_v01_01.tgt",
      "tile_parent": null
    },
    {
      "file": "Metadata/Terrain/Dungeon/NextWalls/dungeon_wall_thin_end_v01_02.tdt",
      "prefix": null,
      "suffix": null,
      "tile_tag": null,
      "room_tag": null,
      "tile_tgt": "Art/Models/Terrain/Jungle/Tiles/VaalInterior/dungeon_wall_thin_end_v01_02.tgt",
      "tile_parent": null
    },
    {
      "file": "Metadata/Terrain/Dungeon/NextWalls/dungeon_wall_thin_pillar_v01_01.tdt",
      "prefix": null,
      "suffix": null,
      "tile_tag": null,
      "room_tag": null,
      "tile_tgt": "Art/Models/Terrain/Jungle/Tiles/VaalInterior/dungeon_wall_thin_pillar_v01_01.tgt",
      "tile_parent": null
    },
    {
      "file": "Metadata/Terrain/Dungeon/NextWalls/dungeon_wall_thin_pillar_v02_01.tdt",
      "prefix": null,
      "suffix": null,
      "tile_tag": null,
      "room_tag": null,
      "tile_tgt": "Art/Models/Terrain/Jungle/Tiles/VaalInterior/dungeon_wall_thin_pillar_v02_01.tgt",
      "tile_parent": null
    },
    {
      "file": "Metadata/Terrain/Dungeon/NextWalls/dungeon_wall_thin_pillar_v03_01.tdt",
      "prefix": null,
      "suffix": null,
      "tile_tag": null,
      "room_tag": null,
      "tile_tgt": "Art/Models/Terrain/Jungle/Tiles/VaalInterior/dungeon_wall_thin_pillar_v03_01.tgt",
      "tile_parent": null
    },
    {
      "file": "Metadata/Terrain/Dungeon/NextWalls/dungeon_wall_thin_pillar_v04_01.tdt",
      "prefix": null,
      "suffix": null,
      "tile_tag": null,
      "room_tag": null,
      "tile_tgt": "Art/Models/Terrain/Jungle/Tiles/VaalInterior/dungeon_wall_thin_pillar_v04_01.tgt",
      "tile_parent": null
    },
    {
      "file": "Metadata/Terrain/Dungeon/NextWalls/dungeon_wall_thin_thick_T_v01_01.tdt",
      "prefix": null,
      "suffix": null,
      "tile_tag": null,
      "room_tag": null,
      "tile_tgt": "Art/Models/Terrain/Jungle/Tiles/VaalInterior/dungeon_wall_thin_thick_T_v01_01.tgt",
      "tile_parent": null
    },
    {
      "file": "Metadata/Terrain/Dungeon/NextWalls/dungeon_wall_thin_thick_X_v01_01.tdt",
      "prefix": null,
      "suffix": null,
      "tile_tag": null,
      "room_tag": null,
      "tile_tgt": "Art/Models/Terrain/Jungle/Tiles/VaalInterior/dungeon_wall_thin_thick_X_v01_01.tgt",
      "tile_parent": null
    },
    {
      "file": "Metadata/Terrain/Dungeon/NextWalls/dungeon_wall_thin_T_v01_01.tdt",
      "prefix": null,
      "suffix": null,
      "tile_tag": null,
      "room_tag": null,
      "tile_tgt": "Art/Models/Terrain/Jungle/Tiles/VaalInterior/dungeon_wall_thin_T_v01_01.tgt",
      "tile_parent": null
    },
    {
      "file": "Metadata/Terrain/Dungeon/NextWalls/dungeon_wall_thin_T_v01_02.tdt",
      "prefix": null,
      "suffix": null,
      "tile_tag": null,
      "room_tag": null,
      "tile_tgt": "Art/Models/Terrain/Jungle/Tiles/VaalInterior/dungeon_wall_thin_T_v01_02.tgt",
      "tile_parent": null
    },
    {
      "file": "Metadata/Terrain/Dungeon/NextWalls/dungeon_wall_thin_v01_01.tdt",
      "prefix": null,
      "suffix": null,
      "tile_tag": null,
      "room_tag": null,
      "tile_tgt": "Art/Models/Terrain/Jungle/Tiles/VaalInterior/dungeon_wall_thin_v01_01.tgt",
      "tile_parent": null
    },
    {
      "file": "Metadata/Terrain/Dungeon/NextWalls/dungeon_wall_thin_v01_02.tdt",
      "prefix": null,
      "suffix": null,
      "tile_tag": null,
      "room_tag": null,
      "tile_tgt": "Art/Models/Terrain/Jungle/Tiles/VaalInterior/dungeon_wall_thin_v01_02.tgt",
      "tile_parent": null
    },
    {
      "file": "Metadata/Terrain/Dungeon/NextWalls/dungeon_wall_thin_X_v01_01.tdt",
      "prefix": null,
      "suffix": null,
      "tile_tag": null,
      "room_tag": null,
      "tile_tgt": "Art/Models/Terrain/Jungle/Tiles/VaalInterior/dungeon_wall_thin_X_v01_01.tgt",
      "tile_parent": null
    },
    {
      "file": "Metadata/Terrain/Dungeon/NextWalls/dungeon_wall_thin_X_v01_02.tdt",
      "prefix": null,
      "suffix": null,
      "tile_tag": null,
      "room_tag": null,
      "tile_tgt": "Art/Models/Terrain/Jungle/Tiles/VaalInterior/dungeon_wall_thin_X_v01_02.tgt",
      "tile_parent": null
    },
    {
      "file": "Metadata/Terrain/Dungeon/Machinarium/ThickwallCurveCc_01.tdt",
      "prefix": null,
      "suffix": null,
      "tile_tag": "LargeCurve",
      "room_tag": null,
      "tile_tgt": "Art/Models/Terrain/Jungle/Tiles/Observatorium/ThickwallCurveCc_02.tgt",
      "tile_parent": null
    },
    {
      "file": "Metadata/Terrain/Dungeon/TreasureVault/Archives_DoorThickWall_01.tdt",
      "prefix": null,
      "suffix": null,
      "tile_tag": "door_facade",
      "room_tag": null,
      "tile_tgt": "Art/Models/Terrain/Jungle/Tiles/VaalInterior/dungeon_DoorThickWall_01.tgt",
      "tile_parent": null
    },
    {
      "file": "Metadata/Terrain/Dungeon/TreasureVault/ArchivesBarrier_01.tdt",
      "prefix": null,
      "suffix": null,
      "tile_tag": "door",
      "room_tag": null,
      "tile_tgt": "Art/Models/Terrain/Jungle/Tiles/TreasureVault/Past/TreasureVault_Barrier/TreasureVaultBarrier_01.tgt",
      "tile_parent": null
    },
    {
      "file": "Metadata/Terrain/Dungeon/TreasureVault/ArchivesHallConcave_01.tdt",
      "prefix": null,
      "suffix": null,
      "tile_tag": null,
      "room_tag": null,
      "tile_tgt": "Art/Models/Terrain/Jungle/Tiles/VaalInterior/dungeon_wall_corner_concave_v02_02.tgt",
      "tile_parent": null
    },
    {
      "file": "Metadata/Terrain/Dungeon/TreasureVault/ArchivesHallConvex_01.tdt",
      "prefix": null,
      "suffix": null,
      "tile_tag": null,
      "room_tag": null,
      "tile_tgt": "Art/Models/Terrain/Jungle/Tiles/VaalInterior/dungeon_wall_corner_convex_v02_01.tgt",
      "tile_parent": null
    },
    {
      "file": "Metadata/Terrain/Dungeon/TreasureVault/ArchivesHallCvCc_01.tdt",
      "prefix": [
        "//"
      ],
      "suffix": null,
      "tile_tag": null,
      "room_tag": null,
      "tile_tgt": null,
      "tile_parent": null
    },
    {
      "file": "Metadata/Terrain/Dungeon/TreasureVault/ThickwallCurveCcCv_02.tdt",
      "prefix": null,
      "suffix": null,
      "tile_tag": "CurvedCcCv",
      "room_tag": null,
      "tile_tgt": "Art/Models/Terrain/Jungle/Tiles/Observatorium/ThickwallCurveCcCv_02.tgt",
      "tile_parent": null
    },
    {
      "file": "Metadata/Terrain/Dungeon/TreasureVault/ArchivesHallDoorway_01.tdt",
      "prefix": null,
      "suffix": null,
      "tile_tag": "halldoorway",
      "room_tag": null,
      "tile_tgt": "Art/Models/Terrain/Jungle/Tiles/VaalInterior/dungeon_entrance_thick_v04_01.tgt",
      "tile_parent": null
    },
    {
      "file": "Metadata/Terrain/Dungeon/TreasureVault/ArchivesHallDoorwayThin_01.tdt",
      "prefix": null,
      "suffix": null,
      "tile_tag": "door",
      "room_tag": null,
      "tile_tgt": "Art/Models/Terrain/Jungle/Tiles/VaalInterior/dungeon_entrance_thin_v01_01.tgt",
      "tile_parent": null
    },
    {
      "file": "Metadata/Terrain/Dungeon/TreasureVault/ArchivesHallEndThin_01.tdt",
      "prefix": null,
      "suffix": null,
      "tile_tag": null,
      "room_tag": null,
      "tile_tgt": "Art/Models/Terrain/Jungle/Tiles/VaalInterior/dungeon_thick_to_thin_v01_01.tgt",
      "tile_parent": null
    },
    {
      "file": "Metadata/Terrain/Dungeon/TreasureVault/ArchivesHallEndThin_02.tdt",
      "prefix": null,
      "suffix": null,
      "tile_tag": null,
      "room_tag": null,
      "tile_tgt": "Art/Models/Terrain/Jungle/Tiles/VaalInterior/dungeon_wall_thin_thick_T_v01_01.tgt",
      "tile_parent": null
    },
    {
      "file": "Metadata/Terrain/Dungeon/TreasureVault/ArchivesHallStraight_01.tdt",
      "prefix": null,
      "suffix": null,
      "tile_tag": null,
      "room_tag": null,
      "tile_tgt": "Art/Models/Terrain/Jungle/Tiles/VaalInterior/dungeon_wall_straight_v01_01.tgt",
      "tile_parent": null
    },
    {
      "file": "Metadata/Terrain/Dungeon/TreasureVault/ArchivesHallToDungeonThin_01.tdt",
      "prefix": null,
      "suffix": null,
      "tile_tag": null,
      "room_tag": null,
      "tile_tgt": "Art/Models/Terrain/Jungle/Tiles/VaalInterior/dungeon_wall_thin_v01_01.tgt",
      "tile_parent": null
    },
    {
      "file": "Metadata/Terrain/Dungeon/TreasureVault/ArchivesThickShelfEndCap_01.tdt",
      "prefix": null,
      "suffix": null,
      "tile_tag": "tallvault",
      "room_tag": null,
      "tile_tgt": "Art/Models/Terrain/Jungle/Tiles/TreasureVault/Past/ThickShelfEndCap_01.tgt",
      "tile_parent": null
    },
    {
      "file": "Metadata/Terrain/Dungeon/TreasureVault/ArchivesThickTallShelfCc_01.tdt",
      "prefix": null,
      "suffix": null,
      "tile_tag": null,
      "room_tag": null,
      "tile_tgt": "Art/Models/Terrain/Jungle/Tiles/TreasureVault/Past/ThickTallShelfCc_01.tgt",
      "tile_parent": null
    },
    {
      "file": "Metadata/Terrain/Dungeon/TreasureVault/ArchivesThickTallShelfEnd_01.tdt",
      "prefix": null,
      "suffix": null,
      "tile_tag": null,
      "room_tag": null,
      "tile_tgt": "Art/Models/Terrain/Jungle/Tiles/TreasureVault/Past/ThickTallShelfEnd_01.tgt",
      "tile_parent": null
    },
    {
      "file": "Metadata/Terrain/Dungeon/TreasureVault/ArchivesThickTallShelfEndCv_01.tdt",
      "prefix": null,
      "suffix": null,
      "tile_tag": null,
      "room_tag": null,
      "tile_tgt": "Art/Models/Terrain/Jungle/Tiles/TreasureVault/Past/ThickTallShelfEndCv_01.tgt",
      "tile_parent": null
    },
    {
      "file": "Metadata/Terrain/Dungeon/TreasureVault/ArchivesThickTallShelfSt_01.tdt",
      "prefix": null,
      "suffix": null,
      "tile_tag": null,
      "room_tag": null,
      "tile_tgt": "Art/Models/Terrain/Jungle/Tiles/TreasureVault/Past/ThickTallShelfSt_01.tgt",
      "tile_parent": null
    },
    {
      "file": "Metadata/Terrain/Dungeon/TreasureVault/ArchivesThickTallShelfSt_02.tdt",
      "prefix": null,
      "suffix": null,
      "tile_tag": "ladder",
      "room_tag": null,
      "tile_tgt": "Art/Models/Terrain/Jungle/Tiles/TreasureVault/Past/ThickTallShelfSt_02.tgt",
      "tile_parent": null
    },
    {
      "file": "Metadata/Terrain/Dungeon/TreasureVault/ArchivesThickTallShelfSt_03.tdt",
      "prefix": null,
      "suffix": null,
      "tile_tag": "shelf",
      "room_tag": null,
      "tile_tgt": "Art/Models/Terrain/Jungle/Tiles/TreasureVault/Past/ThickTallShelfSt_03.tgt",
      "tile_parent": null
    },
    {
      "file": "Metadata/Terrain/Dungeon/TreasureVault/ArchivesThickTallShelfSt_04.tdt",
      "prefix": null,
      "suffix": null,
      "tile_tag": "statue",
      "room_tag": null,
      "tile_tgt": "Art/Models/Terrain/Jungle/Tiles/TreasureVault/Past/ThickTallShelfSt_04.tgt",
      "tile_parent": null
    },
    {
      "file": "Metadata/Terrain/Dungeon/TreasureVault/ArchivesThickTallShelfSt_05.tdt",
      "prefix": null,
      "suffix": null,
      "tile_tag": "desk",
      "room_tag": null,
      "tile_tgt": "Art/Models/Terrain/Jungle/Tiles/TreasureVault/Past/ThickTallShelfSt_05.tgt",
      "tile_parent": null
    },
    {
      "file": "Metadata/Terrain/Dungeon/TreasureVault/ArchivistTile_01.tdt",
      "prefix": null,
      "suffix": null,
      "tile_tag": "Archivist",
      "room_tag": null,
      "tile_tgt": "Art/Models/Terrain/Jungle/Tiles/TreasureVault/Past/ArchivistTile_01.tgt",
      "tile_parent": null
    },
    {
      "file": "Metadata/Terrain/Dungeon/TreasureVault/KnowledgeWingInnerEntrance01_01.tdt",
      "prefix": null,
      "suffix": null,
      "tile_tag": "ArchivesEntrance",
      "room_tag": null,
      "tile_tgt": "Art/Models/Terrain/Jungle/Tiles/TreasureVault/Past/KnowledgeWingInnerEntrance01_01.tgt",
      "tile_parent": null
    },
    {
      "file": "Metadata/Terrain/Dungeon/TreasureVault/TreasureVaultPastFeatures/TreasureWingInnerEntrance_02.tdt",
      "prefix": null,
      "suffix": null,
      "tile_tag": "TreasureGate",
      "room_tag": null,
      "tile_tgt": "Art/Models/Terrain/Jungle/Tiles/TreasureVault/Present/TreasureWingInnerEntrance_02.tgt",
      "tile_parent": null
    },
    {
      "file": "Metadata/Terrain/Dungeon/TreasureVault/VaultToSunken.tdt",
      "prefix": null,
      "suffix": null,
      "tile_tag": "entrance",
      "room_tag": null,
      "tile_tgt": "Art/Models/Terrain/Jungle/Tiles/AreaTransitions/VaultToSunken.tgt",
      "tile_parent": null
    }
  ],
  "version": 25,
  "subgraphs": null,
  "file_groups": null
}