[{"English":[{"condition":[{}],"format":["#"],"index_handlers":[["milliseconds_to_seconds_2dp_if_required"]],"string":"Requiem active time@{0}s"},{"condition":[{"min":1000,"max":1000}],"format":["#"],"index_handlers":[["milliseconds_to_seconds_2dp_if_required"]],"string":"Requiem lasts for {0} second"},{"condition":[{}],"format":["#"],"index_handlers":[["milliseconds_to_seconds_2dp_if_required"]],"string":"Requiem lasts for {0} seconds"}],"ids":["rapidshot_requiem_active_duration_ms"]},{"English":[{"condition":[{}],"format":["#"],"index_handlers":[[]],"string":"Anguish required@{0}"},{"condition":[{}],"format":["#"],"index_handlers":[[]],"string":"Requires {0} anguish to use"}],"ids":["rapidshot_requiem_base_buff_count_requirement"]},{"English":[{"condition":[{}],"format":["#"],"index_handlers":[["per_minute_to_per_second_2dp_if_required"]],"string":"Anguish accumulated per second@{0}"},{"condition":[{}],"format":["#"],"index_handlers":[["per_minute_to_per_second_2dp_if_required"]],"string":"Accumulates {0} anguish per second"}],"ids":["rapidshot_requiem_number_of_stacks_per_minute"]}]